abc_annMacroF1withCost.py
abc_annMacroF1withCost-0.0.1.dist-info/LICENSE.txt
abc_annMacroF1withCost-0.0.1.dist-info/METADATA
abc_annMacroF1withCost-0.0.1.dist-info/WHEEL
abc_annMacroF1withCost-0.0.1.dist-info/top_level.txt
abc_annMacroF1withCost-0.0.1.dist-info/RECORD
