Metadata-Version: 2.1
Name: abc-annMacroF1withCost
Version: 0.0.1
Summary: ABC-ANN-MacroF1withCost is a classification method that combines ABC algorithm with a artificial neural network classification model
Home-page: https://github.com/kagandedeturk/ABC-ANN-MacroF1withCost
Author: Bilge Kagan Dedeturk
Author-email: kagandedeturk@gmail.com
License: UNKNOWN
Platform: UNKNOWN
Classifier: Programming Language :: Python :: 3.7
Classifier: Programming Language :: Python :: 3.10
Classifier: License :: OSI Approved :: BSD License
Classifier: Operating System :: OS Independent
License-File: LICENSE.txt
